Metadata-Version: 2.1
Name: tcgshuffle
Version: 0.1.1
Summary: card shuffle method scorer.
Home-page: UNKNOWN
Author: Yuki Chiba
Author-email: yuki-chiba@outlook.jp
License: UNKNOWN
Platform: UNKNOWN
